{"version":3,"kind":"Article","sha256":"ff78446cf0e6e57851e20b30895fc7d4413454381f5cea1ca31b9c7cf20c87dc","slug":"cv","location":"/cv.md","dependencies":[],"frontmatter":{"title":"CV","content_includes_title":false,"authors":[{"nameParsed":{"literal":"Alex Do","given":"Alex","family":"Do"},"name":"Alex Do","id":"contributors-Users\\b_jav\\Downloads\\student_a8\\digital-portfolio\\myst-generated-uid-0"}],"numbering":{"title":{"offset":1}},"exports":[{"format":"md","filename":"cv.md","url":"/build/cv-0f9b3b2c6bb84cbe6a5ccdeda326e6e1.md"}]},"mdast":{"type":"root","children":[{"type":"block","children":[{"type":"heading","depth":2,"position":{"start":{"line":3,"column":1},"end":{"line":3,"column":1}},"children":[{"type":"strong","position":{"start":{"line":3,"column":1},"end":{"line":3,"column":1}},"children":[{"type":"text","value":"Curriculum Vitae","position":{"start":{"line":3,"column":1},"end":{"line":3,"column":1}},"key":"td4TewH5q2"}],"key":"uydz49gpBs"}],"identifier":"curriculum-vitae","label":"Curriculum Vitae","html_id":"curriculum-vitae","implicit":true,"key":"G5lHOfigBf"},{"type":"paragraph","position":{"start":{"line":5,"column":1},"end":{"line":7,"column":1}},"children":[{"type":"emphasis","position":{"start":{"line":5,"column":1},"end":{"line":5,"column":1}},"children":[{"type":"text","value":"Name:","position":{"start":{"line":5,"column":1},"end":{"line":5,"column":1}},"key":"n914isgpqG"}],"key":"yHH0qpqMWD"},{"type":"text","value":" Alex Do\n","position":{"start":{"line":5,"column":1},"end":{"line":5,"column":1}},"key":"GYYOM7qQBn"},{"type":"emphasis","position":{"start":{"line":5,"column":1},"end":{"line":5,"column":1}},"children":[{"type":"text","value":"Email:","position":{"start":{"line":5,"column":1},"end":{"line":5,"column":1}},"key":"CqMHURxjP8"}],"key":"oHHuk0IASx"},{"type":"text","value":" ","position":{"start":{"line":5,"column":1},"end":{"line":5,"column":1}},"key":"QQFioYAlqI"},{"type":"underline","children":[{"type":"link","url":"mailto:alex.do@email.com","children":[{"type":"text","value":"alex.do@email.com","key":"bDGcMsrHUm"}],"urlSource":"mailto:alex.do@email.com","key":"L1JVqlw7IP"}],"key":"l3KxoYthdC"},{"type":"break","position":{"start":{"line":5,"column":1},"end":{"line":5,"column":1}},"key":"qZDr4aIFyu"},{"type":"emphasis","position":{"start":{"line":5,"column":1},"end":{"line":5,"column":1}},"children":[{"type":"text","value":"Location:","position":{"start":{"line":5,"column":1},"end":{"line":5,"column":1}},"key":"UlZxAvzp8b"}],"key":"i4jGZSG0u5"},{"type":"text","value":" New York, NY","position":{"start":{"line":5,"column":1},"end":{"line":5,"column":1}},"key":"S4kFB6K5mE"}],"key":"wLRHjW04cW"},{"type":"heading","depth":2,"position":{"start":{"line":9,"column":1},"end":{"line":9,"column":1}},"children":[{"type":"text","value":"Summary:","position":{"start":{"line":9,"column":1},"end":{"line":9,"column":1}},"key":"rnMesb3RQR"}],"identifier":"summary","label":"Summary:","html_id":"summary","implicit":true,"key":"b9dhlljqff"},{"type":"paragraph","position":{"start":{"line":10,"column":1},"end":{"line":10,"column":1}},"children":[{"type":"text","value":"As a data scientist with a PhD degree and 5 years of work experience (see my education), I have a deep understanding of statistical modeling, machine learning, and data visualization. My career has been focused on solving complex business problems through the use of data-driven insights, and I have a proven track record of delivering measurable results (see experience section). As a data scientist with a PhD degree and 5 years of work experience (see my education section), I have a deep understanding of statistical modeling, machine learning, and data visualization (more details in skills section). My career has been focused on solving complex business problems through the use of data-driven insights, and I have a proven track record of delivering measurable results (see experience section). Example of my work can be found in analysis_example.ipynb.","position":{"start":{"line":10,"column":1},"end":{"line":10,"column":1}},"key":"pFVkDz1Fdl"}],"key":"wx8UMY4PVA"},{"type":"heading","depth":2,"position":{"start":{"line":12,"column":1},"end":{"line":12,"column":1}},"children":[{"type":"text","value":"Education:","position":{"start":{"line":12,"column":1},"end":{"line":12,"column":1}},"key":"yUmdUAQCHJ"}],"identifier":"education","label":"Education:","html_id":"education","implicit":true,"key":"E89V80fLuM"},{"type":"list","ordered":false,"spread":false,"position":{"start":{"line":13,"column":1},"end":{"line":16,"column":1}},"children":[{"type":"listItem","spread":true,"position":{"start":{"line":13,"column":1},"end":{"line":13,"column":1}},"children":[{"type":"paragraph","children":[{"type":"text","value":"PhD in Computer Science, New York University, 2013-2018","position":{"start":{"line":13,"column":1},"end":{"line":13,"column":1}},"key":"wSrz7SxLkG"}],"key":"kdHlgchSRk"}],"key":"jx4BJzmNwf"},{"type":"listItem","spread":true,"position":{"start":{"line":14,"column":1},"end":{"line":14,"column":1}},"children":[{"type":"paragraph","children":[{"type":"text","value":"MS in Computer Science, University of California, Los Angeles, 2011-2013","position":{"start":{"line":14,"column":1},"end":{"line":14,"column":1}},"key":"owYSOXzcW5"}],"key":"clM0cny8sq"}],"key":"zDfMMHW0Ed"},{"type":"listItem","spread":true,"position":{"start":{"line":15,"column":1},"end":{"line":16,"column":1}},"children":[{"type":"paragraph","children":[{"type":"text","value":"BS in Computer Science, University of Illinois at Urbana-Champaign, 2007-2011","position":{"start":{"line":15,"column":1},"end":{"line":15,"column":1}},"key":"Zt7KErAupC"}],"key":"Qhkd6CSBHO"}],"key":"rbFmUNSeGb"}],"key":"sHV3k2ysXJ"},{"type":"heading","depth":2,"position":{"start":{"line":17,"column":1},"end":{"line":17,"column":1}},"children":[{"type":"text","value":"Skills:","position":{"start":{"line":17,"column":1},"end":{"line":17,"column":1}},"key":"LVhznVxufE"}],"identifier":"skills","label":"Skills:","html_id":"skills","implicit":true,"key":"u5gG2W3Ytr"},{"type":"list","ordered":false,"spread":false,"position":{"start":{"line":18,"column":1},"end":{"line":24,"column":1}},"children":[{"type":"listItem","spread":true,"position":{"start":{"line":18,"column":1},"end":{"line":18,"column":1}},"children":[{"type":"paragraph","children":[{"type":"text","value":"Strong knowledge of statistical modeling and machine learning techniques","position":{"start":{"line":18,"column":1},"end":{"line":18,"column":1}},"key":"gIdJIaso2e"}],"key":"RbedRPSoGY"}],"key":"pNnf0VuiSO"},{"type":"listItem","spread":true,"position":{"start":{"line":19,"column":1},"end":{"line":19,"column":1}},"children":[{"type":"paragraph","children":[{"type":"text","value":"Expertise in data cleaning, feature engineering, and model selection","position":{"start":{"line":19,"column":1},"end":{"line":19,"column":1}},"key":"WhTypoeZG7"}],"key":"ebGhXVAgMo"}],"key":"V3F26nWfuJ"},{"type":"listItem","spread":true,"position":{"start":{"line":20,"column":1},"end":{"line":20,"column":1}},"children":[{"type":"paragraph","children":[{"type":"text","value":"Proficient in programming languages including Python, R, and SQL","position":{"start":{"line":20,"column":1},"end":{"line":20,"column":1}},"key":"RHS5j69bv4"}],"key":"Hu8zNDwha2"}],"key":"Sl9LvgKX2H"},{"type":"listItem","spread":true,"position":{"start":{"line":21,"column":1},"end":{"line":21,"column":1}},"children":[{"type":"paragraph","children":[{"type":"text","value":"Experience with data analysis tools such as Tableau and PowerBI","position":{"start":{"line":21,"column":1},"end":{"line":21,"column":1}},"key":"EJDLuGuo8l"}],"key":"HBJ7LhctKz"}],"key":"uO009CruzI"},{"type":"listItem","spread":true,"position":{"start":{"line":22,"column":1},"end":{"line":22,"column":1}},"children":[{"type":"paragraph","children":[{"type":"text","value":"Excellent project management skills with experience leading cross-functional teams","position":{"start":{"line":22,"column":1},"end":{"line":22,"column":1}},"key":"wxXyipOWfX"}],"key":"LDlOqMbGad"}],"key":"POl4rED97W"},{"type":"listItem","spread":true,"position":{"start":{"line":23,"column":1},"end":{"line":24,"column":1}},"children":[{"type":"paragraph","children":[{"type":"text","value":"Strong communication and presentation skills with the ability to convey complex data insights to both technical and non-technical audiences","position":{"start":{"line":23,"column":1},"end":{"line":23,"column":1}},"key":"HKY5V8NRn0"}],"key":"Go4mAEzFDy"}],"key":"qnsO4JmVKY"}],"key":"p1sm5afjp0"},{"type":"heading","depth":2,"position":{"start":{"line":25,"column":1},"end":{"line":25,"column":1}},"children":[{"type":"text","value":"Professional Experience:","position":{"start":{"line":25,"column":1},"end":{"line":25,"column":1}},"key":"T4i1ZV91Tm"}],"identifier":"professional-experience","label":"Professional Experience:","html_id":"professional-experience","implicit":true,"key":"jsLFm8S40s"},{"type":"paragraph","position":{"start":{"line":26,"column":1},"end":{"line":26,"column":1}},"children":[{"type":"strong","position":{"start":{"line":26,"column":1},"end":{"line":26,"column":1}},"children":[{"type":"text","value":"Data Scientist, ABC Corporation, New York, NY, 2018-present","position":{"start":{"line":26,"column":1},"end":{"line":26,"column":1}},"key":"ouYyuT77e9"}],"key":"WMCMYCvBCf"}],"key":"f6UXNP204I"},{"type":"list","ordered":false,"spread":false,"position":{"start":{"line":27,"column":1},"end":{"line":32,"column":1}},"children":[{"type":"listItem","spread":true,"position":{"start":{"line":27,"column":1},"end":{"line":27,"column":1}},"children":[{"type":"paragraph","children":[{"type":"text","value":"Lead data scientist for a team of five data scientists working on projects in finance, healthcare, and retail industries","position":{"start":{"line":27,"column":1},"end":{"line":27,"column":1}},"key":"SMf5fUtEEN"}],"key":"KZ9GkJpDcj"}],"key":"Ij0AeAxsfi"},{"type":"listItem","spread":true,"position":{"start":{"line":28,"column":1},"end":{"line":28,"column":1}},"children":[{"type":"paragraph","children":[{"type":"text","value":"Developed machine learning models to predict customer churn and identify upsell opportunities for a retail client, resulting in a 20% increase in revenue","position":{"start":{"line":28,"column":1},"end":{"line":28,"column":1}},"key":"r7pEKC4O4q"}],"key":"fQdcaKTL0K"}],"key":"sSfY9vFkKA"},{"type":"listItem","spread":true,"position":{"start":{"line":29,"column":1},"end":{"line":29,"column":1}},"children":[{"type":"paragraph","children":[{"type":"text","value":"Created a dashboard to visualize customer engagement metrics for a healthcare client, resulting in a 15% increase in patient satisfaction scores","position":{"start":{"line":29,"column":1},"end":{"line":29,"column":1}},"key":"qeMHqVl8mV"}],"key":"U1ZK9n1Hbz"}],"key":"kdNMcRlktu"},{"type":"listItem","spread":true,"position":{"start":{"line":30,"column":1},"end":{"line":30,"column":1}},"children":[{"type":"paragraph","children":[{"type":"text","value":"Conducted data analysis and provided recommendations to executive leadership on strategic initiatives","position":{"start":{"line":30,"column":1},"end":{"line":30,"column":1}},"key":"PCUG6mO7eD"}],"key":"DTdySGK635"}],"key":"lVZZgW0mOh"},{"type":"listItem","spread":true,"position":{"start":{"line":31,"column":1},"end":{"line":32,"column":1}},"children":[{"type":"paragraph","children":[{"type":"text","value":"Mentored junior data scientists on best practices for data analysis and machine learning","position":{"start":{"line":31,"column":1},"end":{"line":31,"column":1}},"key":"uwyvclb23E"}],"key":"zKLAnl2TMb"}],"key":"AEKqpW3Qsv"}],"key":"BkhVqwJLgS"},{"type":"paragraph","position":{"start":{"line":33,"column":1},"end":{"line":33,"column":1}},"children":[{"type":"strong","position":{"start":{"line":33,"column":1},"end":{"line":33,"column":1}},"children":[{"type":"text","value":"Data Scientist, XYZ Corporation, Los Angeles, CA, 2016-2018","position":{"start":{"line":33,"column":1},"end":{"line":33,"column":1}},"key":"mIKpl6WlGf"}],"key":"gTc3iGZXp2"}],"key":"wbPWTqAx1E"},{"type":"list","ordered":false,"spread":false,"position":{"start":{"line":34,"column":1},"end":{"line":38,"column":1}},"children":[{"type":"listItem","spread":true,"position":{"start":{"line":34,"column":1},"end":{"line":34,"column":1}},"children":[{"type":"paragraph","children":[{"type":"text","value":"Conducted data analysis to identify opportunities for cost savings in the supply chain, resulting in a 10% reduction in supply chain costs","position":{"start":{"line":34,"column":1},"end":{"line":34,"column":1}},"key":"GuEbO0F5oo"}],"key":"bC7FVOz3Yi"}],"key":"GDjc3pfVAZ"},{"type":"listItem","spread":true,"position":{"start":{"line":35,"column":1},"end":{"line":35,"column":1}},"children":[{"type":"paragraph","children":[{"type":"text","value":"Developed machine learning models to predict customer behavior for a financial client, resulting in a 25% increase in loan approvals","position":{"start":{"line":35,"column":1},"end":{"line":35,"column":1}},"key":"lPMSP3PZIF"}],"key":"qzUr5cBGic"}],"key":"Xeq6yuPoex"},{"type":"listItem","spread":true,"position":{"start":{"line":36,"column":1},"end":{"line":36,"column":1}},"children":[{"type":"paragraph","children":[{"type":"text","value":"Created a dashboard to visualize key performance metrics for a marketing campaign, resulting in a 30% increase in conversions","position":{"start":{"line":36,"column":1},"end":{"line":36,"column":1}},"key":"QetfWEXVzK"}],"key":"mLF9OyxgKL"}],"key":"YzfZEdAaP1"},{"type":"listItem","spread":true,"position":{"start":{"line":37,"column":1},"end":{"line":38,"column":1}},"children":[{"type":"paragraph","children":[{"type":"text","value":"Collaborated with cross-functional teams to develop and implement data-driven solutions","position":{"start":{"line":37,"column":1},"end":{"line":37,"column":1}},"key":"id7AJo5G6C"}],"key":"FBuNlQzYBB"}],"key":"AzGhIxpQYL"}],"key":"I7BQ25X5af"},{"type":"paragraph","position":{"start":{"line":39,"column":1},"end":{"line":39,"column":1}},"children":[{"type":"strong","position":{"start":{"line":39,"column":1},"end":{"line":39,"column":1}},"children":[{"type":"text","value":"Data Analyst, DEF Corporation, Urbana-Champaign, IL, 2011-2016","position":{"start":{"line":39,"column":1},"end":{"line":39,"column":1}},"key":"gOAu9EBdZu"}],"key":"ryOfYojeee"}],"key":"dT6uwUZlkw"},{"type":"list","ordered":false,"spread":false,"position":{"start":{"line":40,"column":1},"end":{"line":43,"column":1}},"children":[{"type":"listItem","spread":true,"position":{"start":{"line":40,"column":1},"end":{"line":40,"column":1}},"children":[{"type":"paragraph","children":[{"type":"text","value":"Conducted data analysis to identify opportunities for process improvement in manufacturing operations","position":{"start":{"line":40,"column":1},"end":{"line":40,"column":1}},"key":"p1dN2gRXWM"}],"key":"L7nVknldOj"}],"key":"DzMaut7gi2"},{"type":"listItem","spread":true,"position":{"start":{"line":41,"column":1},"end":{"line":41,"column":1}},"children":[{"type":"paragraph","children":[{"type":"text","value":"Created reports and dashboards to visualize key performance metrics for executive leadership","position":{"start":{"line":41,"column":1},"end":{"line":41,"column":1}},"key":"D8p3YtU2fz"}],"key":"Pdq017OHND"}],"key":"dzDsNaNrKD"},{"type":"listItem","spread":true,"position":{"start":{"line":42,"column":1},"end":{"line":43,"column":1}},"children":[{"type":"paragraph","children":[{"type":"text","value":"Collaborated with cross-functional teams to implement process improvements","position":{"start":{"line":42,"column":1},"end":{"line":42,"column":1}},"key":"pYZ2wdJooO"}],"key":"KPzfRSvEIX"}],"key":"yNoNGIydb0"}],"key":"eOo7KREx4P"},{"type":"heading","depth":2,"position":{"start":{"line":44,"column":1},"end":{"line":44,"column":1}},"children":[{"type":"text","value":"Certifications:","position":{"start":{"line":44,"column":1},"end":{"line":44,"column":1}},"key":"LhXAhy0yix"}],"identifier":"certifications","label":"Certifications:","html_id":"certifications","implicit":true,"key":"cfo6iKlnYK"},{"type":"paragraph","position":{"start":{"line":45,"column":1},"end":{"line":45,"column":1}},"children":[{"type":"text","value":"To satisfy my eagerness for knowledge, I enroll in online courses in areas of Artificial Intelligence and Software Engineering that pique my interest and undertake independent projects during my leisure hours. A few examples of such projects include:","position":{"start":{"line":45,"column":1},"end":{"line":45,"column":1}},"key":"CI5C4pGzM6"}],"key":"RYK4rb6dZa"},{"type":"list","ordered":false,"spread":false,"position":{"start":{"line":47,"column":1},"end":{"line":55,"column":1}},"children":[{"type":"listItem","spread":true,"position":{"start":{"line":47,"column":1},"end":{"line":47,"column":1}},"children":[{"type":"paragraph","children":[{"type":"text","value":"Microsoft Certified: Azure Data Scientist Associate","position":{"start":{"line":47,"column":1},"end":{"line":47,"column":1}},"key":"dNzmlNNH6a"}],"key":"s2kUhcZfOf"}],"key":"QZAyp3Ha7w"},{"type":"listItem","spread":true,"position":{"start":{"line":48,"column":1},"end":{"line":48,"column":1}},"children":[{"type":"paragraph","children":[{"type":"text","value":"AWS Certified: Machine Learning – Specialty","position":{"start":{"line":48,"column":1},"end":{"line":48,"column":1}},"key":"VkauTUPhK6"}],"key":"Rv9wMhTkOT"}],"key":"Pqb2BIFbuP"},{"type":"listItem","spread":true,"position":{"start":{"line":49,"column":1},"end":{"line":49,"column":1}},"children":[{"type":"paragraph","children":[{"type":"text","value":"Deep Learning Specialization - Coursera","position":{"start":{"line":49,"column":1},"end":{"line":49,"column":1}},"key":"qWOJC1CQlY"}],"key":"lQ0vzuH2Xf"}],"key":"v1nUA68CZZ"},{"type":"listItem","spread":true,"position":{"start":{"line":50,"column":1},"end":{"line":50,"column":1}},"children":[{"type":"paragraph","children":[{"type":"text","value":"Machine Learning Engineer Nanodegree - Udacity","position":{"start":{"line":50,"column":1},"end":{"line":50,"column":1}},"key":"RDht9iZmXP"}],"key":"U0Aafnjrra"}],"key":"icAVjvefKm"},{"type":"listItem","spread":true,"position":{"start":{"line":51,"column":1},"end":{"line":51,"column":1}},"children":[{"type":"paragraph","children":[{"type":"text","value":"React Nanodegree - Udacity\t•\tStatistics Specialization: Introduction to Probability and Data, Inferential Statistics - by Duke University - Coursera","position":{"start":{"line":51,"column":1},"end":{"line":51,"column":1}},"key":"cV7rgSJXSx"}],"key":"QSGx9hmWzm"}],"key":"GvgHlE5yAU"},{"type":"listItem","spread":true,"position":{"start":{"line":52,"column":1},"end":{"line":52,"column":1}},"children":[{"type":"paragraph","children":[{"type":"text","value":"Python Data Science and Machine Learning Bootcamp - Udemy","position":{"start":{"line":52,"column":1},"end":{"line":52,"column":1}},"key":"ruriymIGpo"}],"key":"azucMXJGK0"}],"key":"StUFIiI0uL"},{"type":"listItem","spread":true,"position":{"start":{"line":53,"column":1},"end":{"line":55,"column":1}},"children":[{"type":"paragraph","children":[{"type":"text","value":"Mathematics for Machine Learning Specialization - Coursera","position":{"start":{"line":53,"column":1},"end":{"line":53,"column":1}},"key":"ydFfYWpVAv"}],"key":"aT5AlCi4jg"}],"key":"OUP28TESQw"}],"key":"uT0J0uMxBJ"},{"type":"heading","depth":2,"position":{"start":{"line":56,"column":1},"end":{"line":56,"column":1}},"children":[{"type":"text","value":"Publications:","position":{"start":{"line":56,"column":1},"end":{"line":56,"column":1}},"key":"MYtXY72bkN"}],"identifier":"publications","label":"Publications:","html_id":"publications","implicit":true,"key":"ssEysWkPBO"},{"type":"list","ordered":false,"spread":false,"position":{"start":{"line":57,"column":1},"end":{"line":58,"column":1}},"children":[{"type":"listItem","spread":true,"position":{"start":{"line":57,"column":1},"end":{"line":58,"column":1}},"children":[{"type":"paragraph","children":[{"type":"text","value":"Smith, J., and Jones, L. “A Comparative Analysis of Machine Learning Techniques for Predicting Customer Churn,” Journal of Data Science, Vol. 5, No. 2, 2019.","position":{"start":{"line":57,"column":1},"end":{"line":57,"column":1}},"key":"G8x1MGGHxI"}],"key":"KRWUFe2gm3"}],"key":"zjBn2n5dk0"}],"key":"MfZ9X8AiRG"},{"type":"heading","depth":2,"position":{"start":{"line":59,"column":1},"end":{"line":59,"column":1}},"children":[{"type":"text","value":"Professional Memberships:","position":{"start":{"line":59,"column":1},"end":{"line":59,"column":1}},"key":"PhbNuPO153"}],"identifier":"professional-memberships","label":"Professional Memberships:","html_id":"professional-memberships","implicit":true,"key":"mGHiSdfsQa"},{"type":"list","ordered":false,"spread":false,"position":{"start":{"line":60,"column":1},"end":{"line":62,"column":1}},"children":[{"type":"listItem","spread":true,"position":{"start":{"line":60,"column":1},"end":{"line":60,"column":1}},"children":[{"type":"paragraph","children":[{"type":"text","value":"Member, Data Science Association","position":{"start":{"line":60,"column":1},"end":{"line":60,"column":1}},"key":"dLPyUkovOl"}],"key":"CLIPjFDHXY"}],"key":"Jx5MZptHGT"},{"type":"listItem","spread":true,"position":{"start":{"line":61,"column":1},"end":{"line":61,"column":1}},"children":[{"type":"paragraph","children":[{"type":"text","value":"Member, American Statistical Association","position":{"start":{"line":61,"column":1},"end":{"line":61,"column":1}},"key":"ptSAbWo99y"}],"key":"pVD2lOjOzv"}],"key":"VZKwFeseBv"},{"type":"listItem","spread":true,"position":{"start":{"line":62,"column":1},"end":{"line":62,"column":1}},"children":[{"type":"paragraph","children":[{"type":"text","value":"Member, Institute of Electrical and Electronics Engineers (IEEE)","position":{"start":{"line":62,"column":1},"end":{"line":62,"column":1}},"key":"j1GSORNb3R"}],"key":"ukhCuWNxIi"}],"key":"BhnHvQBk4i"}],"key":"zV7CxB1Gdp"}],"key":"yyXgWjAPYS"}],"key":"JHRz6Ba8En"},"references":{"cite":{"order":[],"data":{}}},"footer":{"navigation":{"prev":{"title":"Digital Portfolio","url":"/","group":"Digital Portfolio"},"next":{"title":"Titanic Dataset: Exploratory Data Analysis","url":"/analysis-example","group":"Example of Analysis"}}},"domain":"http://localhost:3000"}